snapccess/__init__.py
snapccess/model.py
snapccess/train.py
snapccess/util.py
snapccess-0.2.2.dist-info/METADATA
snapccess-0.2.2.dist-info/WHEEL
snapccess-0.2.2.dist-info/RECORD
