Metadata-Version: 2.1
Name: SnapCCESS
Version: 0.2.2
Summary: Ensemble deep learning of embeddings for clustering multimodal single-cell omics data
Author: Lijia Yu
Author-email: yulj2010@gmail.com
Requires-Python: >=3.8
Classifier: Programming Language :: Python :: 3
Classifier: Programming Language :: Python :: 3.8
Classifier: Programming Language :: Python :: 3.9
Classifier: Programming Language :: Python :: 3.10
Classifier: Programming Language :: Python :: 3.11
Classifier: Programming Language :: Python :: 3.12
Requires-Dist: pandas (>=1.5.1)
Requires-Dist: pynvml (>=11.4.1)
Requires-Dist: torch (>=2.2.0)
Requires-Dist: tqdm (>=4.64.1)
